sdk/__init__.py
sdk/absmartly.py
sdk/absmartly_config.py
sdk/audience_deserializer.py
sdk/audience_matcher.py
sdk/client.py
sdk/client_config.py
sdk/context.py
sdk/context_config.py
sdk/context_data_deserializer.py
sdk/context_data_provider.py
sdk/context_event_handler.py
sdk/context_event_logger.py
sdk/context_event_serializer.py
sdk/default_audience_deserializer.py
sdk/default_context_data_deserializer.py
sdk/default_context_data_provider.py
sdk/default_context_event_handler.py
sdk/default_context_event_serializer.py
sdk/default_http_client.py
sdk/default_http_client_config.py
sdk/default_variable_parser.py
sdk/http_client.py
sdk/variable_parser.py
sdk/internal/__init__.py
sdk/internal/buffers.py
sdk/internal/murmur32.py
sdk/internal/variant_assigner.py
sdk/internal/lock/__init__.py
sdk/internal/lock/atomic_bool.py
sdk/internal/lock/atomic_int.py
sdk/internal/lock/concurrency.py
sdk/internal/lock/read_write_lock.py
sdk/json/__init__.py
sdk/json/attribute.py
sdk/json/context_data.py
sdk/json/custom_field_value.py
sdk/json/experiement_application.py
sdk/json/experiment.py
sdk/json/experiment_variant.py
sdk/json/exposure.py
sdk/json/goal_achievement.py
sdk/json/publish_event.py
sdk/json/unit.py
sdk/jsonexpr/evaluator.py
sdk/jsonexpr/expr_evaluator.py
sdk/jsonexpr/json_expr.py
sdk/jsonexpr/operator.py
sdk/jsonexpr/operators/and_combinator.py
sdk/jsonexpr/operators/binary_operator.py
sdk/jsonexpr/operators/boolean_combinator.py
sdk/jsonexpr/operators/equals_operator.py
sdk/jsonexpr/operators/greater_than_operator.py
sdk/jsonexpr/operators/greater_than_or_equal_operator.py
sdk/jsonexpr/operators/in_operator.py
sdk/jsonexpr/operators/less_than_operator.py
sdk/jsonexpr/operators/less_than_or_equal_operator.py
sdk/jsonexpr/operators/match_operator.py
sdk/jsonexpr/operators/not_operator.py
sdk/jsonexpr/operators/null_operator.py
sdk/jsonexpr/operators/or_combinator.py
sdk/jsonexpr/operators/unary_operator.py
sdk/jsonexpr/operators/value_operator.py
ABSmartly-0.2.4.dist-info/LICENSE
ABSmartly-0.2.4.dist-info/METADATA
ABSmartly-0.2.4.dist-info/WHEEL
ABSmartly-0.2.4.dist-info/top_level.txt
ABSmartly-0.2.4.dist-info/RECORD
