Metadata-Version: 2.1
Name: ABSmartly
Version: 0.2.4
Summary: ABSmartly Python SDK lib
Author-email: ABSmartly <info@ABSmartly.com>
License: The MIT License (MIT)
Project-URL: Homepage, https://github.com/absmartly/python3-sdk
Keywords: ABSmartly,SDK,Testing
Classifier: License :: OSI Approved :: MIT License
Classifier: Programming Language :: Python
Classifier: Programming Language :: Python :: 3
Requires-Python: >=3.9
License-File: LICENSE
Requires-Dist: requests>=2.28.1
Requires-Dist: urllib3>=1.26.12
Requires-Dist: jsons>=1.6.3
Provides-Extra: dev
Requires-Dist: black; extra == "dev"
Requires-Dist: bumpver; extra == "dev"
Requires-Dist: isort; extra == "dev"
Requires-Dist: pip-tools; extra == "dev"
Requires-Dist: pytest; extra == "dev"
